fancylogging/__init__.py
fancylogging/_version.py
fancylogging-0.0.4.dist-info/METADATA
fancylogging-0.0.4.dist-info/WHEEL
fancylogging-0.0.4.dist-info/top_level.txt
fancylogging-0.0.4.dist-info/RECORD
