Metadata-Version: 2.1
Name: fancylogging
Version: 0.0.4
Summary: hassle-free nicely-formatted console and file logging in Python
Author-email: tempookian <tempookian@gmail.com>
Project-URL: Homepage, https://github.com/tempookian/fancylogging
Project-URL: Bug Tracker, https://github.com/tempookian/fancylogging/issues
Classifier: Programming Language :: Python :: 3
Classifier: License :: OSI Approved :: MIT License
Classifier: Operating System :: OS Independent
Requires-Python: >=3.8
Requires-Dist: python_json_logger<3.0.0,>=2.0.7
Requires-Dist: rich<14.0.0,>=13.7.0
Requires-Dist: fancylogging
